transcripter/__init__.py
transcripter/config.py
transcripter/logs.py
transcripter/core/__init__.py
transcripter/core/redis_manager.py
transcripter/core/youtube_manager.py
transcripter/services/__init__.py
transcripter/services/indexing_service.py
transcripter/services/search_service.py
transcripter-0.1.0.dist-info/METADATA
transcripter-0.1.0.dist-info/WHEEL
transcripter-0.1.0.dist-info/entry_points.txt
transcripter-0.1.0.dist-info/licenses/LICENSE
transcripter-0.1.0.dist-info/RECORD
