Metadata-Version: 2.3
Name: transcripter
Version: 0.1.0
Summary: A tool for indexing and searching YouTube transcripts.
Project-URL: Homepage, https://github.com/0xRy4n/transcripter
Project-URL: Bug Tracker, https://github.com/0xRy4n/transcripter/issues
Author-email: Ryan Gordon <mail@ry4n.sh>
License-File: LICENSE
Classifier: License :: OSI Approved :: MIT License
Classifier: Operating System :: OS Independent
Classifier: Programming Language :: Python :: 3
Requires-Python: >=3.7
Requires-Dist: flask
Requires-Dist: loguru
Requires-Dist: python-dotenv
Requires-Dist: python-youtube
Requires-Dist: pyyaml
Requires-Dist: redis
Requires-Dist: redisearch
Requires-Dist: youtube-transcript-api
Provides-Extra: dev
Requires-Dist: mock; extra == 'dev'
